iasimplesetup-0.0.4.dist-info/RECORD
iasimplesetup-0.0.4.dist-info/WHEEL
iasimplesetup-0.0.4.dist-info/top_level.txt
iasimplesetup-0.0.4.dist-info/METADATA
iasimplesetup/__init__.cpython-313-i386-linux-musl.so
