Metadata-Version: 2.1
Name: iasimplesetup
Version: 0.0.4
Author-email: Innovations Anonymous <InnovAnon-Inc@gmx.com>
Requires-Python: >=3.11
Requires-Dist: Cython
Requires-Dist: setuptools>=64
Requires-Dist: structlog
Requires-Dist: toml
Requires-Dist: wheel
